LICENSE
MANIFEST.in
README.rst
bootstrap.py
buildout.cfg
setup.py
cs/__init__.py
cs.zestreleaser.upload.egg-info/PKG-INFO
cs.zestreleaser.upload.egg-info/SOURCES.txt
cs.zestreleaser.upload.egg-info/dependency_links.txt
cs.zestreleaser.upload.egg-info/entry_points.txt
cs.zestreleaser.upload.egg-info/namespace_packages.txt
cs.zestreleaser.upload.egg-info/not-zip-safe
cs.zestreleaser.upload.egg-info/requires.txt
cs.zestreleaser.upload.egg-info/top_level.txt
cs/zestreleaser/__init__.py
cs/zestreleaser/upload/__init__.py
cs/zestreleaser/upload/upload.py
docs/HISTORY.txt
docs/INSTALL.txt
docs/LICENSE.GPL
docs/LICENSE.txt